setup.py
BitnFly/__init__.py
BitnFly/app.py
BitnFly/api/__init__.py
BitnFly/tests/__init__.py
BitnFly/tests/test_bits_fly.py
bitnfly.egg-info/PKG-INFO
bitnfly.egg-info/SOURCES.txt
bitnfly.egg-info/dependency_links.txt
bitnfly.egg-info/requires.txt
bitnfly.egg-info/top_level.txt